ROM.sv
module ROM #(
    parameter AW = 10,  // Address Width: 2^10 = 1024 palabras (4 KB)
    parameter DW = 32   // Data Width: 32 bits por instrucción
) (
    input  logic [AW-1:0] address,  // Dirección en palabras (no en bytes)
    output logic [DW-1:0] data      // Instrucción entregada
);

    // Memoria ROM interna
    logic [DW-1:0] mem [0:(1<<AW)-1];  // 1024 palabras de 32 bits = 4 KB

    // Inicializar desde archivo externo en formato hexadecimal
    initial begin
        $readmemh("prog.hex", mem); // Carga archivo desde "prog.hex" 
    end

    // Lectura asíncrona: respuesta inmediata
    assign data = mem[address];

endmodule

tb_ROM.sv
`timescale 1ns/1ps
module tb_ROM;

    //-----------------------
    // Parámetros de la ROM
    //-----------------------
    localparam AW          = 10;               // 2^10 = 1024 palabras
    localparam DW          = 32;
    localparam MAX_WORDS   = 1<<AW;            // 1024
    localparam MAX_PRINT   = 256;              // Imprime, como máximo, 256 líneas

    //-----------------------
    // Señales bajo prueba
    //-----------------------
    logic [AW-1:0] address;
    logic [DW-1:0] data;

    //-----------------------
    // Instancia de la ROM
    //-----------------------
    ROM #(.AW(AW), .DW(DW)) dut (
        .address(address),
        .data   (data)
    );

    //-----------------------
    // Proceso de lectura
    //-----------------------
    integer  i;
    integer  instr_cnt;

    initial begin
        $display("\n==== INICIO  TEST  ROM ====");
        $dumpfile("tb_ROM.vcd");
        $dumpvars(0,tb_ROM);

        //----------------------------------------------
        // Esperar a que $readmemh termine su ejecución
        //----------------------------------------------
        #10;             // tiempo suficiente tras la fase 0‑ns

        instr_cnt = 0;
        address   = '0;  // asegurarse de empezar en la palabra 0
        #1;

        // Recorrer la ROM palabra por palabra
        for (i = 0; i < MAX_WORDS; i++) begin
            address = i;
            #1;         // tiempo de lectura asíncrona de la ROM

            // Si los 32 bits contienen X o Z ⇒ la dirección no está inicializada
            if (^data === 1'bx || ^data === 1'bz) begin
                $display("---> Parada: celda %0d no inicializada (data = %08h)", i, data);
                break;
            end

            //------------------------------------------
            // Imprimir las primeras MAX_PRINT palabras
            //------------------------------------------
            if (i < MAX_PRINT)
                $display("ROM[%0d] = 0x%08x", i, data);

            instr_cnt++;
        end

        $display("\nTotal de instrucciones validas encontradas: %0d", instr_cnt);

        // Sencilla validación empírica:
        if (instr_cnt != 123) begin
            $error("La ROM NO contiene las 123 instrucciones esperadas; encontro %0d", instr_cnt);
            $fatal;
        end
        else
            $display("La ROM contiene exactamente las 123 palabras de Gambling_Tec.hex");

        $display("==== FIN   TEST  ROM ====\n");
        $finish;
    end
endmodule

simulation/modelsim/tb_ROM.vcd
$date
	Tue Jun 17 16:11:25 2025
$end
$version
	ModelSim Version 10.5b
$end
$timescale
	1ps
$end

$scope module tb_ROM $end
$var parameter 32 ! AW $end
$var parameter 32 " DW $end
$var parameter 32 # MAX_WORDS $end
$var parameter 32 $ MAX_PRINT $end
$var reg 10 % address [9:0] $end
$var reg 32 & data [31:0] $end
$var integer 32 ' i $end
$var integer 32 ( instr_cnt $end

$scope module dut $end
$var parameter 32 ) AW $end
$var parameter 32 * DW $end
$var wire 1 + address [9] $end
$var wire 1 , address [8] $end
$var wire 1 - address [7] $end
$var wire 1 . address [6] $end
$var wire 1 / address [5] $end
$var wire 1 0 address [4] $end
$var wire 1 1 address [3] $end
$var wire 1 2 address [2] $end
$var wire 1 3 address [1] $end
$var wire 1 4 address [0] $end
$var reg 32 5 data [31:0] $end
$upscope $end
$upscope $end
$enddefinitions $end
#0
$dumpvars
bx %
bx &
bx 5
b1010 !
b100000 "
b10000000000 #
b100000000 $
b1010 )
b100000 *
bx '
bx (
x4
x3
x2
x1
x0
x/
x.
x-
x,
x+
$end
#10000
b0 (
b0 %
04
03
02
01
00
0/
0.
0-
0,
0+
b11100010100000000000000000000000 5
b11100010100000000000000000000000 &
#11000
b0 '
#12000
b1 (
b1 '
b1 %
14
b11100010100000000000000000010100 5
b11100010100000000000000000010100 &
#13000
b10 (
b10 '
b10 %
04
13
b11100010100000010001000000000000 5
b11100010100000010001000000000000 &
#14000
b11 (
b11 '
b11 %
14
b11100101100000000001000000000000 5
b11100101100000000001000000000000 &
#15000
b100 (
b100 '
b100 %
04
03
12
b11100010100000000000000000000100 5
b11100010100000000000000000000100 &
#16000
b101 (
b101 '
b101 %
14
b11100010100000100010000000000000 5
b11100010100000100010000000000000 &
#17000
b110 (
b110 '
b110 %
04
13
b11100010100000100010000000101000 5
b11100010100000100010000000101000 &
#18000
b111 (
b111 '
b111 %
14
b11100001010100000000000000000010 5
b11100001010100000000000000000010 &
#19000
b1000 (
b1000 '
b1000 %
04
03
02
11
b11011010111111111111111111111001 5
b11011010111111111111111111111001 &
#20000
b1001 (
b1001 '
b1001 %
14
b11100010100000000000000000000000 5
b11100010100000000000000000000000 &
#21000
b1010 (
b1010 '
b1010 %
04
13
b11100010100000000000000000010100 5
b11100010100000000000000000010100 &
#22000
b1011 (
b1011 '
b1011 %
14
b11100010100000010001000000000000 5
b11100010100000010001000000000000 &
#23000
b1100 (
b1100 '
b1100 %
04
03
12
b11100101100000000001000000000000 5
b11100101100000000001000000000000 &
#24000
b1101 (
b1101 '
b1101 %
14
b11100010100000000000000000000000 5
b11100010100000000000000000000000 &
#25000
b1110 (
b1110 '
b1110 %
04
13
b11100010100000000000000000001010 5
b11100010100000000000000000001010 &
#26000
b1111 (
b1111 '
b1111 %
14
b11100101100100000001000000000000 5
b11100101100100000001000000000000 &
#27000
b10000 (
b10000 '
b10000 %
04
03
02
01
10
b11100010100000100010000000000000 5
b11100010100000100010000000000000 &
#28000
b10001 (
b10001 '
b10001 %
14
b11100010100000100010000001110101 5
b11100010100000100010000001110101 &
#29000
b10010 (
b10010 '
b10010 %
04
13
b11100001010100010000000000000010 5
b11100001010100010000000000000010 &
#30000
b10011 (
b10011 '
b10011 %
14
b1010000000000000000000001100 5
b1010000000000000000000001100 &
#31000
b10100 (
b10100 '
b10100 %
04
03
12
b11100010100000100010000000000000 5
b11100010100000100010000000000000 &
#32000
b10101 (
b10101 '
b10101 %
14
b11100010100000100010000001110010 5
b11100010100000100010000001110010 &
#33000
b10110 (
b10110 '
b10110 %
04
13
b11100001010100010000000000000010 5
b11100001010100010000000000000010 &
#34000
b10111 (
b10111 '
b10111 %
14
b1010000000000000000000011100 5
b1010000000000000000000011100 &
#35000
b11000 (
b11000 '
b11000 %
04
03
02
11
b11100010100000100010000000000000 5
b11100010100000100010000000000000 &
#36000
b11001 (
b11001 '
b11001 %
14
b11100010100000100010000001100110 5
b11100010100000100010000001100110 &
#37000
b11010 (
b11010 '
b11010 %
04
13
b11100001010100010000000000000010 5
b11100001010100010000000000000010 &
#38000
b11011 (
b11011 '
b11011 %
14
b1010000000000000000000100100 5
b1010000000000000000000100100 &
#39000
b11100 (
b11100 '
b11100 %
04
03
12
b11100010100000100010000000000000 5
b11100010100000100010000000000000 &
#40000
b11101 (
b11101 '
b11101 %
14
b11100010100000100010000001011010 5
b11100010100000100010000001011010 &
#41000
b11110 (
b11110 '
b11110 %
04
13
b11100001010100010000000000000010 5
b11100001010100010000000000000010 &
#42000
b11111 (
b11111 '
b11111 %
14
b1010000000000000000000100101 5
b1010000000000000000000100101 &
#43000
b100000 (
b100000 '
b100000 %
04
03
02
01
00
1/
b11101010111111111111111111101011 5
b11101010111111111111111111101011 &
#44000
b100001 (
b100001 '
b100001 %
14
b11100010100000000000000000000000 5
b11100010100000000000000000000000 &
#45000
b100010 (
b100010 '
b100010 %
04
13
b11100010100000000000000000010100 5
b11100010100000000000000000010100 &
#46000
b100011 (
b100011 '
b100011 %
14
b11100101100100000001000000000000 5
b11100101100100000001000000000000 &
#47000
b100100 (
b100100 '
b100100 %
04
03
12
b11100010100000010001000000000001 5
b11100010100000010001000000000001 &
#48000
b100101 (
b100101 '
b100101 %
14
b11100010100000100010000000000000 5
b11100010100000100010000000000000 &
#49000
b100110 (
b100110 '
b100110 %
04
13
b11100010100000100010000011111111 5
b11100010100000100010000011111111 &
#50000
b100111 (
b100111 '
b100111 %
14
#51000
b101000 (
b101000 '
b101000 %
04
03
02
11
#52000
b101001 (
b101001 '
b101001 %
14
b11100010100000100010000011101010 5
b11100010100000100010000011101010 &
#53000
b101010 (
b101010 '
b101010 %
04
13
b11100001010100010000000000000010 5
b11100001010100010000000000000010 &
#54000
b101011 (
b101011 '
b101011 %
14
b11001010000000000000000000000001 5
b11001010000000000000000000000001 &
#55000
b101100 (
b101100 '
b101100 %
04
03
12
b11100101100000000001000000000000 5
b11100101100000000001000000000000 &
#56000
b101101 (
b101101 '
b101101 %
14
b11101010111111111111111111011110 5
b11101010111111111111111111011110 &
#57000
b101110 (
b101110 '
b101110 %
04
13
b11100010100000010001000000000000 5
b11100010100000010001000000000000 &
#58000
b101111 (
b101111 '
b101111 %
14
b11100010100000010001000011111111 5
b11100010100000010001000011111111 &
#59000
b110000 (
b110000 '
b110000 %
04
03
02
01
10
#60000
b110001 (
b110001 '
b110001 %
14
#61000
b110010 (
b110010 '
b110010 %
04
13
b11100010100000010001000011101010 5
b11100010100000010001000011101010 &
#62000
b110011 (
b110011 '
b110011 %
14
b11100101100000000001000000000000 5
b11100101100000000001000000000000 &
#63000
b110100 (
b110100 '
b110100 %
04
03
12
b11101010111111111111111111010111 5
b11101010111111111111111111010111 &
#64000
b110101 (
b110101 '
b110101 %
14
b11100010100000000000000000000000 5
b11100010100000000000000000000000 &
#65000
b110110 (
b110110 '
b110110 %
04
13
b11100010100000000000000000010100 5
b11100010100000000000000000010100 &
#66000
b110111 (
b110111 '
b110111 %
14
b11100101100100000001000000000000 5
b11100101100100000001000000000000 &
#67000
b111000 (
b111000 '
b111000 %
04
03
02
11
b11100010100000100010000000000000 5
b11100010100000100010000000000000 &
#68000
b111001 (
b111001 '
b111001 %
14
b11100001010100010000000000000010 5
b11100001010100010000000000000010 &
#69000
b111010 (
b111010 '
b111010 %
04
13
b1010000000000000000000000010 5
b1010000000000000000000000010 &
#70000
b111011 (
b111011 '
b111011 %
14
b11100010010000010001000000000001 5
b11100010010000010001000000000001 &
#71000
b111100 (
b111100 '
b111100 %
04
03
12
b11100101100000000001000000000000 5
b11100101100000000001000000000000 &
#72000
b111101 (
b111101 '
b111101 %
14
b11101010111111111111111111001110 5
b11101010111111111111111111001110 &
#73000
b111110 (
b111110 '
b111110 %
04
13
b11100010100000010001000000000000 5
b11100010100000010001000000000000 &
#74000
b111111 (
b111111 '
b111111 %
14
b11100101100000000001000000000000 5
b11100101100000000001000000000000 &
#75000
b1000000 (
b1000000 '
b1000000 %
04
03
02
01
00
0/
1.
b11101010111111111111111111001011 5
b11101010111111111111111111001011 &
#76000
b1000001 (
b1000001 '
b1000001 %
14
b11100010100000000000000000000000 5
b11100010100000000000000000000000 &
#77000
b1000010 (
b1000010 '
b1000010 %
04
13
b11100010100000000000000000010100 5
b11100010100000000000000000010100 &
#78000
b1000011 (
b1000011 '
b1000011 %
14
b11100010100000010001000000000000 5
b11100010100000010001000000000000 &
#79000
b1000100 (
b1000100 '
b1000100 %
04
03
12
b11100101100000000001000000000000 5
b11100101100000000001000000000000 &
#80000
b1000101 (
b1000101 '
b1000101 %
14
b11101010111111111111111111000110 5
b11101010111111111111111111000110 &
#81000
b1000110 (
b1000110 '
b1000110 %
04
13
b11100010100001000100000000000000 5
b11100010100001000100000000000000 &
#82000
b1000111 (
b1000111 '
b1000111 %
14
b11100010100000000000000000000000 5
b11100010100000000000000000000000 &
#83000
b1001000 (
b1001000 '
b1001000 %
04
03
02
11
b11100010100000000000000000001010 5
b11100010100000000000000000001010 &
#84000
b1001001 (
b1001001 '
b1001001 %
14
b11100101100100000001000000000000 5
b11100101100100000001000000000000 &
#85000
b1001010 (
b1001010 '
b1001010 %
04
13
b11100010100000100010000000000000 5
b11100010100000100010000000000000 &
#86000
b1001011 (
b1001011 '
b1001011 %
14
b11100010100000100010000000101001 5
b11100010100000100010000000101001 &
#87000
b1001100 (
b1001100 '
b1001100 %
04
03
12
b11100001010100010000000000000010 5
b11100001010100010000000000000010 &
#88000
b1001101 (
b1001101 '
b1001101 %
14
b1010000000000000000000000110 5
b1010000000000000000000000110 &
#89000
b1001110 (
b1001110 '
b1001110 %
04
13
b11100010100001000100000000000001 5
b11100010100001000100000000000001 &
#90000
b1001111 (
b1001111 '
b1001111 %
14
b11100010100000110011000000000000 5
b11100010100000110011000000000000 &
#91000
b1010000 (
b1010000 '
b1010000 %
04
03
02
01
10
b11100010100000110011000000000011 5
b11100010100000110011000000000011 &
#92000
b1010001 (
b1010001 '
b1010001 %
14
b11100001010101000000000000000011 5
b11100001010101000000000000000011 &
#93000
b1010010 (
b1010010 '
b1010010 %
04
13
b11011010111111111111111111110011 5
b11011010111111111111111111110011 &
#94000
b1010011 (
b1010011 '
b1010011 %
14
b11100010100001000100000000000000 5
b11100010100001000100000000000000 &
#95000
b1010100 (
b1010100 '
b1010100 %
04
03
12
b11101010111111111111111111110001 5
b11101010111111111111111111110001 &
#96000
b1010101 (
b1010101 '
b1010101 %
14
b11100010100000000000000000000000 5
b11100010100000000000000000000000 &
#97000
b1010110 (
b1010110 '
b1010110 %
04
13
b11100010100000000000000000011000 5
b11100010100000000000000000011000 &
#98000
b1010111 (
b1010111 '
b1010111 %
14
b11100101100000000100000000000000 5
b11100101100000000100000000000000 &
#99000
b1011000 (
b1011000 '
b1011000 %
04
03
02
11
b11100010100001010101000000000000 5
b11100010100001010101000000000000 &
#100000
b1011001 (
b1011001 '
b1011001 %
14
b11100010100000000000000000000000 5
b11100010100000000000000000000000 &
#101000
b1011010 (
b1011010 '
b1011010 %
04
13
b11100010100000000000000000001010 5
b11100010100000000000000000001010 &
#102000
b1011011 (
b1011011 '
b1011011 %
14
b11100101100100000001000000000000 5
b11100101100100000001000000000000 &
#103000
b1011100 (
b1011100 '
b1011100 %
04
03
12
b11100010100000100010000000000000 5
b11100010100000100010000000000000 &
#104000
b1011101 (
b1011101 '
b1011101 %
14
b11100010100000100010000000101001 5
b11100010100000100010000000101001 &
#105000
b1011110 (
b1011110 '
b1011110 %
04
13
b11100001010100010000000000000010 5
b11100001010100010000000000000010 &
#106000
b1011111 (
b1011111 '
b1011111 %
14
b1010000000000000000000000110 5
b1010000000000000000000000110 &
#107000
b1100000 (
b1100000 '
b1100000 %
04
03
02
01
00
1/
b11100010100001010101000000000001 5
b11100010100001010101000000000001 &
#108000
b1100001 (
b1100001 '
b1100001 %
14
b11100010100000110011000000000000 5
b11100010100000110011000000000000 &
#109000
b1100010 (
b1100010 '
b1100010 %
04
13
b11100010100000110011000000000011 5
b11100010100000110011000000000011 &
#110000
b1100011 (
b1100011 '
b1100011 %
14
b11100001010101010000000000000011 5
b11100001010101010000000000000011 &
#111000
b1100100 (
b1100100 '
b1100100 %
04
03
12
b11011010111111111111111111110011 5
b11011010111111111111111111110011 &
#112000
b1100101 (
b1100101 '
b1100101 %
14
b11100010100001010101000000000000 5
b11100010100001010101000000000000 &
#113000
b1100110 (
b1100110 '
b1100110 %
04
13
b11101010111111111111111111110001 5
b11101010111111111111111111110001 &
#114000
b1100111 (
b1100111 '
b1100111 %
14
b11100010100000000000000000000000 5
b11100010100000000000000000000000 &
#115000
b1101000 (
b1101000 '
b1101000 %
04
03
02
11
b11100010100000000000000000011100 5
b11100010100000000000000000011100 &
#116000
b1101001 (
b1101001 '
b1101001 %
14
b11100101100000000101000000000000 5
b11100101100000000101000000000000 &
#117000
b1101010 (
b1101010 '
b1101010 %
04
13
b11100010100001100110000000000000 5
b11100010100001100110000000000000 &
#118000
b1101011 (
b1101011 '
b1101011 %
14
b11100010100000000000000000000000 5
b11100010100000000000000000000000 &
#119000
b1101100 (
b1101100 '
b1101100 %
04
03
12
b11100010100000000000000000001010 5
b11100010100000000000000000001010 &
#120000
b1101101 (
b1101101 '
b1101101 %
14
b11100101100100000001000000000000 5
b11100101100100000001000000000000 &
#121000
b1101110 (
b1101110 '
b1101110 %
04
13
b11100010100000100010000000000000 5
b11100010100000100010000000000000 &
#122000
b1101111 (
b1101111 '
b1101111 %
14
b11100010100000100010000000101001 5
b11100010100000100010000000101001 &
#123000
b1110000 (
b1110000 '
b1110000 %
04
03
02
01
10
b11100001010100010000000000000010 5
b11100001010100010000000000000010 &
#124000
b1110001 (
b1110001 '
b1110001 %
14
b1010000000000000000000000110 5
b1010000000000000000000000110 &
#125000
b1110010 (
b1110010 '
b1110010 %
04
13
b11100010100001100110000000000001 5
b11100010100001100110000000000001 &
#126000
b1110011 (
b1110011 '
b1110011 %
14
b11100010100000110011000000000000 5
b11100010100000110011000000000000 &
#127000
b1110100 (
b1110100 '
b1110100 %
04
03
12
b11100010100000110011000000000011 5
b11100010100000110011000000000011 &
#128000
b1110101 (
b1110101 '
b1110101 %
14
b11100001010101100000000000000011 5
b11100001010101100000000000000011 &
#129000
b1110110 (
b1110110 '
b1110110 %
04
13
b11011010111111111111111111110011 5
b11011010111111111111111111110011 &
#130000
b1110111 (
b1110111 '
b1110111 %
14
b11100010100001100110000000000000 5
b11100010100001100110000000000000 &
#131000
b1111000 (
b1111000 '
b1111000 %
04
03
02
11
b11101010111111111111111111110001 5
b11101010111111111111111111110001 &
#132000
b1111001 (
b1111001 '
b1111001 %
14
b11100010100000000000000000000000 5
b11100010100000000000000000000000 &
#133000
b1111010 (
b1111010 '
b1111010 %
04
13
b11100010100000000000000000100000 5
b11100010100000000000000000100000 &
#134000
b1111011 (
b1111011 '
b1111011 %
14
b11100101100000000110000000000000 5
b11100101100000000110000000000000 &
#135000
b1111100 (
b1111100 '
b1111100 %
04
03
12
b11100001010101000000000000000101 5
b11100001010101000000000000000101 &
#136000
b1111101 (
b1111101 '
b1111101 %
14
b11010000000000000000000011100 5
b11010000000000000000000011100 &
#137000
b1111110 (
b1111110 '
b1111110 %
04
13
b11100001010101000000000000000110 5
b11100001010101000000000000000110 &
#138000
b1111111 (
b1111111 '
b1111111 %
14
b11010000000000000000000011010 5
b11010000000000000000000011010 &
#139000
b10000000 (
b10000000 '
b10000000 %
04
03
02
01
00
0/
0.
1-
b11100010100000000000000000000000 5
b11100010100000000000000000000000 &
#140000
b10000001 (
b10000001 '
b10000001 %
14
b11100010100000000000000000100100 5
b11100010100000000000000000100100 &
#141000
b10000010 (
b10000010 '
b10000010 %
04
13
b11100010100000010001000000000000 5
b11100010100000010001000000000000 &
#142000
b10000011 (
b10000011 '
b10000011 %
14
b11100010100000010001000000000010 5
b11100010100000010001000000000010 &
#143000
b10000100 (
b10000100 '
b10000100 %
04
03
12
b11100101100000000001000000000000 5
b11100101100000000001000000000000 &
#144000
b10000101 (
b10000101 '
b10000101 %
14
b11100010100000000000000000000000 5
b11100010100000000000000000000000 &
#145000
b10000110 (
b10000110 '
b10000110 %
04
13
b11100010100000000000000000010100 5
b11100010100000000000000000010100 &
#146000
b10000111 (
b10000111 '
b10000111 %
14
b11100101100100000001000000000000 5
b11100101100100000001000000000000 &
#147000
b10001000 (
b10001000 '
b10001000 %
04
03
02
11
b11100010100000100010000000000000 5
b11100010100000100010000000000000 &
#148000
b10001001 (
b10001001 '
b10001001 %
14
b11100010100000100010000000001010 5
b11100010100000100010000000001010 &
#149000
b10001010 (
b10001010 '
b10001010 %
04
13
b11100000100000010001000000000010 5
b11100000100000010001000000000010 &
#150000
b10001011 (
b10001011 '
b10001011 %
14
b11100010100000100010000000000000 5
b11100010100000100010000000000000 &
#151000
b10001100 (
b10001100 '
b10001100 %
04
03
12
b11100010100000100010000011111111 5
b11100010100000100010000011111111 &
#152000
b10001101 (
b10001101 '
b10001101 %
14
#153000
b10001110 (
b10001110 '
b10001110 %
04
13
#154000
b10001111 (
b10001111 '
b10001111 %
14
b11100010100000100010000011101010 5
b11100010100000100010000011101010 &
#155000
b10010000 (
b10010000 '
b10010000 %
04
03
02
01
10
b11100001010100010000000000000010 5
b11100001010100010000000000000010 &
#156000
b10010001 (
b10010001 '
b10010001 %
14
b11001010000000000000000000000001 5
b11001010000000000000000000000001 &
#157000
b10010010 (
b10010010 '
b10010010 %
04
13
b11100101100000000001000000000000 5
b11100101100000000001000000000000 &
#158000
b10010011 (
b10010011 '
b10010011 %
14
b11101010111111111111111101111000 5
b11101010111111111111111101111000 &
#159000
b10010100 (
b10010100 '
b10010100 %
04
03
12
b11100010100000010001000000000000 5
b11100010100000010001000000000000 &
#160000
b10010101 (
b10010101 '
b10010101 %
14
b11100010100000010001000011111111 5
b11100010100000010001000011111111 &
#161000
b10010110 (
b10010110 '
b10010110 %
04
13
#162000
b10010111 (
b10010111 '
b10010111 %
14
#163000
b10011000 (
b10011000 '
b10011000 %
04
03
02
11
b11100010100000010001000011101010 5
b11100010100000010001000011101010 &
#164000
b10011001 (
b10011001 '
b10011001 %
14
b11100101100000000001000000000000 5
b11100101100000000001000000000000 &
#165000
b10011010 (
b10011010 '
b10011010 %
04
13
b11101010111111111111111101110001 5
b11101010111111111111111101110001 &
#166000
b10011011 (
b10011011 '
b10011011 %
14
b11100010100000000000000000000000 5
b11100010100000000000000000000000 &
#167000
b10011100 (
b10011100 '
b10011100 %
04
03
12
b11100010100000000000000000100100 5
b11100010100000000000000000100100 &
#168000
b10011101 (
b10011101 '
b10011101 %
14
b11100010100000010001000000000000 5
b11100010100000010001000000000000 &
#169000
b10011110 (
b10011110 '
b10011110 %
04
13
b11100010100000010001000000000001 5
b11100010100000010001000000000001 &
#170000
b10011111 (
b10011111 '
b10011111 %
14
b11100101100000000001000000000000 5
b11100101100000000001000000000000 &
#171000
b10100000 (
b10100000 '
b10100000 %
04
03
02
01
00
1/
b11100010100000000000000000000000 5
b11100010100000000000000000000000 &
#172000
b10100001 (
b10100001 '
b10100001 %
14
b11100010100000000000000000010100 5
b11100010100000000000000000010100 &
#173000
b10100010 (
b10100010 '
b10100010 %
04
13
b11100101100100000001000000000000 5
b11100101100100000001000000000000 &
#174000
b10100011 (
b10100011 '
b10100011 %
14
b11100010100000100010000000000000 5
b11100010100000100010000000000000 &
#175000
b10100100 (
b10100100 '
b10100100 %
04
03
12
b11100010100000100010000000001010 5
b11100010100000100010000000001010 &
#176000
b10100101 (
b10100101 '
b10100101 %
14
b11100001010100010000000000000010 5
b11100001010100010000000000000010 &
#177000
b10100110 (
b10100110 '
b10100110 %
04
13
b10111010000000000000000000000010 5
b10111010000000000000000000000010 &
#178000
b10100111 (
b10100111 '
b10100111 %
14
b11100000010000010001000000000010 5
b11100000010000010001000000000010 &
#179000
b10101000 (
b10101000 '
b10101000 %
04
03
02
11
b11100101100000000001000000000000 5
b11100101100000000001000000000000 &
#180000
b10101001 (
b10101001 '
b10101001 %
14
b11101010111111111111111101100010 5
b11101010111111111111111101100010 &
#181000
b10101010 (
b10101010 '
b10101010 %
04
13
b11100010100000010001000000000000 5
b11100010100000010001000000000000 &
#182000
b10101011 (
b10101011 '
b10101011 %
14
b11100101100000000001000000000000 5
b11100101100000000001000000000000 &
#183000
b10101100 (
b10101100 '
b10101100 %
04
03
12
b11101010111111111111111101011111 5
b11101010111111111111111101011111 &
#184000
b10101101 (
b10101101 '
b10101101 %
14
bx 5
bx &
