ROM.sv
module ROM #(
    parameter AW = 10,  // Address Width: 2^10 = 1024 palabras (4 KB)
    parameter DW = 32   // Data Width: 32 bits por instrucción
) (
    input  logic [AW-1:0] address,  // Dirección en palabras (no en bytes)
    output logic [DW-1:0] data      // Instrucción entregada
);

    // Memoria ROM interna
    logic [DW-1:0] mem [0:(1<<AW)-1];  // 1024 palabras de 32 bits = 4 KB

    // Inicializar desde archivo externo en formato hexadecimal
    initial begin
        $readmemh("prog.hex", mem); // Carga archivo desde "prog.hex" 
    end

    // Lectura asíncrona: respuesta inmediata
    assign data = mem[address];

endmodule

tb_ROM.sv
`timescale 1ns/1ps
module tb_ROM;

    //-----------------------
    // Parámetros de la ROM
    //-----------------------
    localparam AW          = 10;               // 2^10 = 1024 palabras
    localparam DW          = 32;
    localparam MAX_WORDS   = 1<<AW;            // 1024
    localparam MAX_PRINT   = 256;              // Imprime, como máximo, 256 líneas

    //-----------------------
    // Señales bajo prueba
    //-----------------------
    logic [AW-1:0] address;
    logic [DW-1:0] data;

    //-----------------------
    // Instancia de la ROM
    //-----------------------
    ROM #(.AW(AW), .DW(DW)) dut (
        .address(address),
        .data   (data)
    );

    //-----------------------
    // Proceso de lectura
    //-----------------------
    integer  i;
    integer  instr_cnt;

    initial begin
        $display("\n==== INICIO  TEST  ROM ====");
        $dumpfile("tb_ROM.vcd");
        $dumpvars(0,tb_ROM);

        //----------------------------------------------
        // Esperar a que $readmemh termine su ejecución
        //----------------------------------------------
        #10;             // tiempo suficiente tras la fase 0‑ns

        instr_cnt = 0;
        address   = '0;  // asegurarse de empezar en la palabra 0
        #1;

        // Recorrer la ROM palabra por palabra
        for (i = 0; i < MAX_WORDS; i++) begin
            address = i;
            #1;         // tiempo de lectura asíncrona de la ROM

            // Si los 32 bits contienen X o Z ⇒ la dirección no está inicializada
            if (^data === 1'bx || ^data === 1'bz) begin
                $display("---> Parada: celda %0d no inicializada (data = %08h)", i, data);
                break;
            end

            //------------------------------------------
            // Imprimir las primeras MAX_PRINT palabras
            //------------------------------------------
            if (i < MAX_PRINT)
                $display("ROM[%0d] = 0x%08x", i, data);

            instr_cnt++;
        end

        $display("\nTotal de instrucciones validas encontradas: %0d", instr_cnt);

        // Sencilla validación empírica:
        if (instr_cnt != 123) begin
            $error("La ROM NO contiene las 123 instrucciones esperadas; encontro %0d", instr_cnt);
            $fatal;
        end
        else
            $display("La ROM contiene exactamente las 123 palabras de Gambling_Tec.hex");

        $display("==== FIN   TEST  ROM ====\n");
        $finish;
    end
endmodule

simulation/modelsim/tb_ROM.vcd
$date
	Tue Jun 17 22:26:12 2025
$end
$version
	ModelSim Version 10.5b
$end
$timescale
	1ps
$end

$scope module tb_ROM $end
$var parameter 32 ! AW $end
$var parameter 32 " DW $end
$var parameter 32 # MAX_WORDS $end
$var parameter 32 $ MAX_PRINT $end
$var reg 10 % address [9:0] $end
$var reg 32 & data [31:0] $end
$var integer 32 ' i $end
$var integer 32 ( instr_cnt $end

$scope module dut $end
$var parameter 32 ) AW $end
$var parameter 32 * DW $end
$var wire 1 + address [9] $end
$var wire 1 , address [8] $end
$var wire 1 - address [7] $end
$var wire 1 . address [6] $end
$var wire 1 / address [5] $end
$var wire 1 0 address [4] $end
$var wire 1 1 address [3] $end
$var wire 1 2 address [2] $end
$var wire 1 3 address [1] $end
$var wire 1 4 address [0] $end
$var reg 32 5 data [31:0] $end
$upscope $end
$upscope $end
$enddefinitions $end
#0
$dumpvars
bx %
bx &
bx 5
b1010 !
b100000 "
b10000000000 #
b100000000 $
b1010 )
b100000 *
bx '
bx (
x4
x3
x2
x1
x0
x/
x.
x-
x,
x+
$end
#10000
b0 (
b0 %
04
03
02
01
00
0/
0.
0-
0,
0+
b11100101100100100001000000000000 5
b11100101100100100001000000000000 &
#11000
b0 '
#12000
b1 (
b1 '
b1 %
14
b11100101100100100010000000000100 5
b11100101100100100010000000000100 &
#13000
b10 (
b10 '
b10 %
04
13
b11100000100000010011000000000010 5
b11100000100000010011000000000010 &
#14000
b11 (
b11 '
b11 %
14
b11100000010000100100000000000001 5
b11100000010000100100000000000001 &
#15000
b100 (
b100 '
b100 %
04
03
12
b11100000000000010101000000000010 5
b11100000000000010101000000000010 &
#16000
b101 (
b101 '
b101 %
14
b11100001100000010110000000000010 5
b11100001100000010110000000000010 &
#17000
b110 (
b110 '
b110 %
04
13
b11100001010100010000000000000010 5
b11100001010100010000000000000010 &
#18000
b111 (
b111 '
b111 %
14
b10111010000000000000000000000101 5
b10111010000000000000000000000101 &
#19000
b1000 (
b1000 '
b1000 %
04
03
02
11
b11100000100000110111000000000100 5
b11100000100000110111000000000100 &
#20000
b1001 (
b1001 '
b1001 %
14
b11100101100000100111000000001000 5
b11100101100000100111000000001000 &
#21000
b1010 (
b1010 '
b1010 %
04
13
b11100001010101110000000000000111 5
b11100001010101110000000000000111 &
#22000
b1011 (
b1011 '
b1011 %
14
b1010111111111111111111111111 5
b1010111111111111111111111111 &
#23000
b1100 (
b1100 '
b1100 %
04
03
12
b11100000010001111000000000000011 5
b11100000010001111000000000000011 &
#24000
b1101 (
b1101 '
b1101 %
14
b11101010000000000000000000000001 5
b11101010000000000000000000000001 &
#25000
b1110 (
b1110 '
b1110 %
04
13
b11100000100000011001000000000001 5
b11100000100000011001000000000001 &
#26000
b1111 (
b1111 '
b1111 %
14
b11101010111111111111111111110111 5
b11101010111111111111111111110111 &
#27000
b10000 (
b10000 '
b10000 %
04
03
02
01
10
b11101010111111111111111111111110 5
b11101010111111111111111111111110 &
#28000
b10001 (
b10001 '
b10001 %
14
bx 5
bx &
