ROM.sv
module ROM #(
    parameter AW = 10,  // Address Width: 2^10 = 1024 palabras (4 KB)
    parameter DW = 32   // Data Width: 32 bits por instrucción
) (
    input  logic [AW-1:0] address,  // Dirección en palabras (no en bytes)
    output logic [DW-1:0] data      // Instrucción entregada
);

    // Memoria ROM interna
    logic [DW-1:0] mem [0:(1<<AW)-1];  // 1024 palabras de 32 bits = 4 KB

    // Inicializar desde archivo externo en formato hexadecimal
    initial begin
        $readmemh("prog.hex", mem); // Carga archivo desde "prog.hex" 
    end

    // Lectura asíncrona: respuesta inmediata
    assign data = mem[address];

endmodule

tb_ROM.sv
`timescale 1ns/1ps

module tb_ROM;

    logic [9:0] address;         // 10 bits = 1024 instrucciones (4 KB)
    logic [31:0] data;           // Instruccion entregada por la ROM

    // Instancia del modulo ROM
    ROM #(.AW(10)) dut (
        .address(address),
        .data(data)
    );

    // Simulacion
    initial begin
        $display("==== INICIO TEST ROM ====");
        $dumpfile("tb_ROM.vcd");
        $dumpvars(0, tb_ROM);

        // Esperando que se cargue la ROM
        #10;

        // Leer las primeras 4 instrucciones
        address = 0;
        #5;
        $display("ROM[0] = 0x%08x", data);

        address = 1;
        #5;
        $display("ROM[1] = 0x%08x", data);

        address = 2;
        #5;
        $display("ROM[2] = 0x%08x", data);

        address = 3;
        #5;
        $display("ROM[3] = 0x%08x", data);

        $finish;
    end

endmodule

simulation/questa/tb_ROM.vcd
$date
	Sun Jun 15 19:39:57 2025
$end
$version
	Questa Intel Starter FPGA Edition Version 2023.3
$end
$timescale
	1ps
$end

$scope module tb_ROM $end
$var reg 10 ! address [9:0] $end
$var reg 32 " data [31:0] $end

$scope module dut $end
$var parameter 32 # AW $end
$var parameter 32 $ DW $end
$var wire 1 % address [9] $end
$var wire 1 & address [8] $end
$var wire 1 ' address [7] $end
$var wire 1 ( address [6] $end
$var wire 1 ) address [5] $end
$var wire 1 * address [4] $end
$var wire 1 + address [3] $end
$var wire 1 , address [2] $end
$var wire 1 - address [1] $end
$var wire 1 . address [0] $end
$var reg 32 / data [31:0] $end
$upscope $end
$upscope $end
$enddefinitions $end
#0
$dumpvars
bx !
bx "
bx /
b1010 #
b100000 $
x.
x-
x,
x+
x*
x)
x(
x'
x&
x%
$end
#10000
b0 !
0.
0-
0,
0+
0*
0)
0(
0'
0&
0%
b11100101100100100001000000000000 /
b11100101100100100001000000000000 "
#15000
b1 !
1.
b11100000100000010011000000000001 /
b11100000100000010011000000000001 "
#20000
b10 !
0.
1-
b11100101100100100100000000000100 /
b11100101100100100100000000000100 "
#25000
b11 !
1.
b11100000100000110101000000000100 /
b11100000100000110101000000000100 "
#30000
b100 !
0.
0-
1,
b11100000100001010110000000000101 /
b11100000100001010110000000000101 "
#35000
b101 !
1.
b11101010111111111111111111111110 /
b11101010111111111111111111111110 "
#40000
b110 !
0.
1-
bx /
bx "
